README.md
setup.py
iptk/__init__.py
iptk/dataset.py
iptk/dataset_store.py
iptk.egg-info/PKG-INFO
iptk.egg-info/SOURCES.txt
iptk.egg-info/dependency_links.txt
iptk.egg-info/requires.txt
iptk.egg-info/top_level.txt
iptk/metadata/__init__.py
iptk/metadata/set.py
iptk/metadata/spec.py
iptk/utils/__init__.py
iptk/utils/docker_image.py
iptk/utils/job.py
iptk/utils/json.py