Metadata-Version: 1.1
Name: iptk
Version: 0.4.1
Summary: Python interface to the Imaging Pipeline Toolkit
Home-page: https://github.com/iptk/iptk-py
Author: Jan-Gerd Tenberge
Author-email: jan-gerd.tenberge@uni-muenster.de
License: UNKNOWN
Download-URL: https://github.com/iptk/iptk-py/archive/0.4.tar.gz
Keywords: neuroimaging,docker
Platform: UNKNOWN
